[{"line":1,"elements":[{"line":3,"name":"","description":"","type":"background","keyword":"Background","steps":[{"name":"configure driver = { type: 'chrome' }","result":{"duration":26710400,"status":"passed"},"match":{"location":"karate","arguments":[]},"keyword":"*","line":4,"doc_string":{"content_type":"","value":"10:44:52.231 karate.env system property was: null \n","line":4}}]},{"start_timestamp":"2024-05-18T05:14:52.127Z","line":49,"name":"validate complete flow of the application","description":"","id":"validate-complete-flow-of-the-application","type":"scenario","keyword":"Scenario Outline","steps":[{"name":"driver 'https:\/\/www.saucedemo.com\/'","result":{"duration":3357733500,"status":"passed"},"match":{"location":"karate","arguments":[]},"keyword":"Given","line":7},{"name":"input('#user-name', 'standard_user')","result":{"duration":249519100,"status":"passed"},"match":{"location":"karate","arguments":[]},"keyword":"And","line":8},{"name":"input('#password', 'secret_sauce')","result":{"duration":134227000,"status":"passed"},"match":{"location":"karate","arguments":[]},"keyword":"And","line":9},{"name":"delay(2000)","result":{"duration":2010796200,"status":"passed"},"match":{"location":"karate","arguments":[]},"keyword":"*","line":10},{"name":"click('#login-button')","result":{"duration":50323500,"status":"passed"},"match":{"location":"karate","arguments":[]},"keyword":"And","line":11},{"name":"driver.maximize()","result":{"duration":26489300,"status":"passed"},"match":{"location":"karate","arguments":[]},"keyword":"*","line":12},{"name":"delay(2000)","result":{"duration":2010274000,"status":"passed"},"match":{"location":"karate","arguments":[]},"keyword":"*","line":13},{"name":"driver 'https:\/\/www.saucedemo.com\/inventory.html'","result":{"duration":149040800,"status":"passed"},"match":{"location":"karate","arguments":[]},"comments":["#Add items to cart and verify in the cart page"],"keyword":"Given","line":15},{"name":"waitFor(\"\/\/button[text()='Add to cart']\").exists","result":{"duration":23915900,"status":"passed"},"match":{"location":"karate","arguments":[]},"keyword":"*","line":16},{"name":"def addToCartButtons = driver.locateAll(\"\/\/button[text()='Add to cart']\")","result":{"duration":7286400,"status":"passed"},"match":{"location":"karate","arguments":[]},"keyword":"*","line":17},{"name":"def itemCount = addToCartButtons.length","result":{"duration":1921300,"status":"passed"},"match":{"location":"karate","arguments":[]},"keyword":"*","line":18},{"name":"print 'Total Add to Cart buttons: ', itemCount","result":{"duration":2157700,"status":"passed"},"match":{"location":"karate","arguments":[]},"keyword":"*","line":19,"doc_string":{"content_type":"","value":"10:45:00.309 [print] Total Add to Cart buttons:  6 \n","line":19}},{"name":"eval karate.forEach(addToCartButtons, button => driver.click(button.locator))","result":{"duration":37416500,"status":"passed"},"match":{"location":"karate","arguments":[]},"keyword":"*","line":20},{"name":"driver.click(\"\/\/a[@class='shopping_cart_link']\")","result":{"duration":13141800,"status":"passed"},"match":{"location":"karate","arguments":[]},"keyword":"*","line":21},{"name":"driver 'https:\/\/www.saucedemo.com\/cart.html'","result":{"duration":80528500,"status":"passed"},"match":{"location":"karate","arguments":[]},"keyword":"Given","line":22},{"name":"def cartItems = driver.locateAll(\"\/\/div[@class='cart_item']\")","result":{"duration":5335700,"status":"passed"},"match":{"location":"karate","arguments":[]},"keyword":"*","line":23},{"name":"def cartItemCount = cartItems.length","result":{"duration":1716600,"status":"passed"},"match":{"location":"karate","arguments":[]},"keyword":"*","line":24},{"name":"print 'Total items in the cart: ', cartItemCount","result":{"duration":2164100,"status":"passed"},"match":{"location":"karate","arguments":[]},"keyword":"*","line":25,"doc_string":{"content_type":"","value":"10:45:00.450 [print] Total items in the cart:  6 \n","line":25}},{"name":"click(\"\/\/button[@id='remove-sauce-labs-backpack']\")","result":{"duration":7642900,"status":"passed"},"match":{"location":"karate","arguments":[]},"comments":["#remove item from the cart"],"keyword":"And","line":27},{"name":"delay(1000)","result":{"duration":1011427300,"status":"passed"},"match":{"location":"karate","arguments":[]},"keyword":"*","line":28},{"name":"scroll(\"\/\/button[@id='continue-shopping']\").click()","result":{"duration":30806600,"status":"passed"},"match":{"location":"karate","arguments":[]},"keyword":"And","line":29},{"name":"driver 'https:\/\/www.saucedemo.com\/inventory.html'","result":{"duration":90816600,"status":"passed"},"match":{"location":"karate","arguments":[]},"keyword":"Given","line":30},{"name":"click(\"\/\/button[@id='add-to-cart-sauce-labs-backpack']\")","result":{"duration":7292900,"status":"passed"},"match":{"location":"karate","arguments":[]},"comments":["#add new item to cart"],"keyword":"And","line":32},{"name":"click(\"\/\/a[@class='shopping_cart_link']\")","result":{"duration":13389800,"status":"passed"},"match":{"location":"karate","arguments":[]},"keyword":"And","line":33},{"name":"delay(1000)","result":{"duration":1013488900,"status":"passed"},"match":{"location":"karate","arguments":[]},"keyword":"*","line":34},{"name":"scroll(\"\/\/button[@id='checkout']\").click()","result":{"duration":20250000,"status":"passed"},"match":{"location":"karate","arguments":[]},"keyword":"And","line":35},{"name":"focus('#first-name')","result":{"duration":10994400,"status":"passed"},"match":{"location":"karate","arguments":[]},"keyword":"And","line":36},{"name":"input('#first-name','Rutvi')","result":{"duration":35710900,"status":"passed"},"match":{"location":"karate","arguments":[]},"keyword":"And","line":37},{"name":"input('#last-name','Mohta')","result":{"duration":32911600,"status":"passed"},"match":{"location":"karate","arguments":[]},"keyword":"And","line":38},{"name":"input('#postal-code','422101')","result":{"duration":30427200,"status":"passed"},"match":{"location":"karate","arguments":[]},"keyword":"And","line":39},{"name":"click(\"\/\/input[@id='continue']\")","result":{"duration":9466800,"status":"passed"},"match":{"location":"karate","arguments":[]},"keyword":"And","line":40},{"name":"driver 'https:\/\/www.saucedemo.com\/checkout-step-two.html'","result":{"duration":131171700,"status":"passed"},"match":{"location":"karate","arguments":[]},"keyword":"Given","line":41},{"name":"click(\"\/\/button[@name='finish']\")","result":{"duration":13150400,"status":"passed"},"match":{"location":"karate","arguments":[]},"keyword":"And","line":42},{"name":"delay(1000)","result":{"duration":1012463000,"status":"passed"},"match":{"location":"karate","arguments":[]},"keyword":"And","line":43},{"name":"driver 'https:\/\/www.saucedemo.com\/checkout-complete.html'","result":{"duration":91880500,"status":"passed"},"match":{"location":"karate","arguments":[]},"keyword":"Given","line":44},{"name":"click(\"\/\/button[@class='btn btn_primary btn_small']\")","result":{"duration":17904200,"status":"passed"},"match":{"location":"karate","arguments":[]},"keyword":"And","line":45}],"tags":[]}],"name":"com\/ui\/automation\/completeflow\/entireFlow.feature","description":"Complete flow of the application","id":"complete-flow-of-the-application","keyword":"Feature","uri":"com\/ui\/automation\/completeflow\/entireFlow.feature"}]